{
  "ball_track": [
    {
      "timestamp": 0.0,
      "x": 52.5,
      "y": 34.0
    },
    {
      "timestamp": 0.2,
      "x": 52.76,
      "y": 34.59
    },
    {
      "timestamp": 0.4,
      "x": 52.9,
      "y": 35.17
    },
    {
      "timestamp": 0.6,
      "x": 52.48,
      "y": 34.97
    },
    {
      "timestamp": 0.8,
      "x": 52.27,
      "y": 35.06
    },
    {
      "timestamp": 1.0,
      "x": 53.4,
      "y": 34.83
    },
    {
      "timestamp": 1.2,
      "x": 54.9,
      "y": 33.95
    },
    {
      "timestamp": 1.4,
      "x": 54.83,
      "y": 34.89
    },
    {
      "timestamp": 1.6,
      "x": 56.32,
      "y": 34.84
    },
    {
      "timestamp": 1.8,
      "x": 57.64,
      "y": 34.53
    },
    {
      "timestamp": 2.0,
      "x": 57.2,
      "y": 35.46
    },
    {
      "timestamp": 2.2,
      "x": 56.75,
      "y": 36.82
    },
    {
      "timestamp": 2.4,
      "x": 56.02,
      "y": 37.49
    },
    {
      "timestamp": 2.6,
      "x": 55.58,
      "y": 36.43
    },
    {
      "timestamp": 2.8,
      "x": 54.43,
      "y": 37.58
    },
    {
      "timestamp": 3.0,
      "x": 53.79,
      "y": 36.31
    },
    {
      "timestamp": 3.2,
      "x": 54.32,
      "y": 35.46
    },
    {
      "timestamp": 3.4,
      "x": 54.43,
      "y": 35.03
    },
    {
      "timestamp": 3.6,
      "x": 55.36,
      "y": 36.47
    },
    {
      "timestamp": 3.8,
      "x": 54.34,
      "y": 37.78
    },
    {
      "timestamp": 4.0,
      "x": 53.0,
      "y": 36.87
    },
    {
      "timestamp": 4.2,
      "x": 52.6,
      "y": 35.81
    },
    {
      "timestamp": 4.4,
      "x": 51.6,
      "y": 34.87
    },
    {
      "timestamp": 4.6,
      "x": 52.56,
      "y": 35.5
    },
    {
      "timestamp": 4.8,
      "x": 51.9,
      "y": 34.54
    },
    {
      "timestamp": 5.0,
      "x": 52.42,
      "y": 34.69
    },
    {
      "timestamp": 5.2,
      "x": 52.6,
      "y": 33.77
    },
    {
      "timestamp": 5.4,
      "x": 53.2,
      "y": 35.02
    },
    {
      "timestamp": 5.6,
      "x": 51.75,
      "y": 33.66
    },
    {
      "timestamp": 5.8,
      "x": 52.88,
      "y": 32.26
    },
    {
      "timestamp": 6.0,
      "x": 53.68,
      "y": 31.33
    },
    {
      "timestamp": 6.2,
      "x": 54.18,
      "y": 32.11
    },
    {
      "timestamp": 6.4,
      "x": 52.69,
      "y": 32.13
    },
    {
      "timestamp": 6.6,
      "x": 52.61,
      "y": 31.52
    },
    {
      "timestamp": 6.8,
      "x": 53.59,
      "y": 31.48
    },
    {
      "timestamp": 7.0,
      "x": 53.97,
      "y": 32.01
    },
    {
      "timestamp": 7.2,
      "x": 54.26,
      "y": 30.99
    },
    {
      "timestamp": 7.4,
      "x": 52.93,
      "y": 29.59
    },
    {
      "timestamp": 7.6,
      "x": 51.95,
      "y": 28.71
    },
    {
      "timestamp": 7.8,
      "x": 51.06,
      "y": 27.36
    },
    {
      "timestamp": 8.0,
      "x": 50.76,
      "y": 28.64
    },
    {
      "timestamp": 8.2,
      "x": 50.08,
      "y": 28.71
    },
    {
      "timestamp": 8.4,
      "x": 50.31,
      "y": 28.69
    },
    {
      "timestamp": 8.6,
      "x": 51.51,
      "y": 28.44
    },
    {
      "timestamp": 8.8,
      "x": 50.66,
      "y": 28.04
    },
    {
      "timestamp": 9.0,
      "x": 50.24,
      "y": 27.62
    },
    {
      "timestamp": 9.2,
      "x": 50.76,
      "y": 27.91
    },
    {
      "timestamp": 9.4,
      "x": 51.89,
      "y": 28.07
    },
    {
      "timestamp": 9.6,
      "x": 53.11,
      "y": 27.31
    },
    {
      "timestamp": 9.8,
      "x": 52.17,
      "y": 28.62
    },
    {
      "timestamp": 10.0,
      "x": 53.15,
      "y": 29.04
    },
    {
      "timestamp": 10.2,
      "x": 53.37,
      "y": 28.02
    },
    {
      "timestamp": 10.4,
      "x": 52.24,
      "y": 29.23
    },
    {
      "timestamp": 10.6,
      "x": 53.27,
      "y": 28.2
    },
    {
      "timestamp": 10.8,
      "x": 52.23,
      "y": 28.22
    },
    {
      "timestamp": 11.0,
      "x": 52.99,
      "y": 27.21
    },
    {
      "timestamp": 11.2,
      "x": 53.98,
      "y": 26.9
    },
    {
      "timestamp": 11.4,
      "x": 54.92,
      "y": 26.33
    },
    {
      "timestamp": 11.6,
      "x": 55.74,
      "y": 26.24
    },
    {
      "timestamp": 11.8,
      "x": 55.88,
      "y": 24.88
    },
    {
      "timestamp": 12.0,
      "x": 56.17,
      "y": 26.15
    },
    {
      "timestamp": 12.2,
      "x": 56.75,
      "y": 27.05
    },
    {
      "timestamp": 12.4,
      "x": 56.43,
      "y": 25.73
    },
    {
      "timestamp": 12.6,
      "x": 55.01,
      "y": 24.52
    },
    {
      "timestamp": 12.8,
      "x": 54.78,
      "y": 23.76
    },
    {
      "timestamp": 13.0,
      "x": 55.69,
      "y": 25.18
    },
    {
      "timestamp": 13.2,
      "x": 56.92,
      "y": 24.29
    },
    {
      "timestamp": 13.4,
      "x": 58.0,
      "y": 23.8
    },
    {
      "timestamp": 13.6,
      "x": 57.99,
      "y": 23.23
    },
    {
      "timestamp": 13.8,
      "x": 58.36,
      "y": 23.19
    },
    {
      "timestamp": 14.0,
      "x": 58.79,
      "y": 24.18
    },
    {
      "timestamp": 14.2,
      "x": 58.52,
      "y": 23.64
    },
    {
      "timestamp": 14.4,
      "x": 59.92,
      "y": 22.16
    },
    {
      "timestamp": 14.6,
      "x": 60.48,
      "y": 20.85
    },
    {
      "timestamp": 14.8,
      "x": 60.39,
      "y": 20.63
    },
    {
      "timestamp": 15.0,
      "x": 61.05,
      "y": 21.5
    },
    {
      "timestamp": 15.2,
      "x": 61.86,
      "y": 22.95
    },
    {
      "timestamp": 15.4,
      "x": 60.69,
      "y": 23.27
    },
    {
      "timestamp": 15.6,
      "x": 60.89,
      "y": 22.16
    },
    {
      "timestamp": 15.8,
      "x": 60.72,
      "y": 22.97
    },
    {
      "timestamp": 16.0,
      "x": 61.62,
      "y": 23.52
    },
    {
      "timestamp": 16.2,
      "x": 62.11,
      "y": 22.25
    },
    {
      "timestamp": 16.4,
      "x": 60.95,
      "y": 23.3
    },
    {
      "timestamp": 16.6,
      "x": 61.03,
      "y": 24.77
    },
    {
      "timestamp": 16.8,
      "x": 61.95,
      "y": 25.95
    },
    {
      "timestamp": 17.0,
      "x": 61.21,
      "y": 27.38
    },
    {
      "timestamp": 17.2,
      "x": 62.2,
      "y": 27.88
    },
    {
      "timestamp": 17.4,
      "x": 62.42,
      "y": 29.14
    },
    {
      "timestamp": 17.6,
      "x": 62.1,
      "y": 27.74
    },
    {
      "timestamp": 17.8,
      "x": 62.44,
      "y": 28.29
    },
    {
      "timestamp": 18.0,
      "x": 62.52,
      "y": 28.05
    },
    {
      "timestamp": 18.2,
      "x": 63.61,
      "y": 27.48
    },
    {
      "timestamp": 18.4,
      "x": 62.89,
      "y": 26.18
    },
    {
      "timestamp": 18.6,
      "x": 62.74,
      "y": 25.44
    },
    {
      "timestamp": 18.8,
      "x": 63.59,
      "y": 26.21
    },
    {
      "timestamp": 19.0,
      "x": 63.22,
      "y": 25.9
    },
    {
      "timestamp": 19.2,
      "x": 63.59,
      "y": 26.21
    },
    {
      "timestamp": 19.4,
      "x": 62.13,
      "y": 25.21
    },
    {
      "timestamp": 19.6,
      "x": 62.37,
      "y": 26.66
    },
    {
      "timestamp": 19.8,
      "x": 63.55,
      "y": 26.36
    },
    {
      "timestamp": 20.0,
      "x": 63.35,
      "y": 26.21
    },
    {
      "timestamp": 20.2,
      "x": 61.88,
      "y": 25.85
    },
    {
      "timestamp": 20.4,
      "x": 61.09,
      "y": 26.96
    },
    {
      "timestamp": 20.6,
      "x": 60.74,
      "y": 25.46
    },
    {
      "timestamp": 20.8,
      "x": 59.97,
      "y": 26.17
    },
    {
      "timestamp": 21.0,
      "x": 60.11,
      "y": 26.07
    },
    {
      "timestamp": 21.2,
      "x": 60.58,
      "y": 27.53
    },
    {
      "timestamp": 21.4,
      "x": 60.6,
      "y": 26.18
    },
    {
      "timestamp": 21.6,
      "x": 60.01,
      "y": 25.51
    },
    {
      "timestamp": 21.8,
      "x": 60.41,
      "y": 25.33
    },
    {
      "timestamp": 22.0,
      "x": 61.79,
      "y": 24.99
    },
    {
      "timestamp": 22.2,
      "x": 62.29,
      "y": 26.4
    },
    {
      "timestamp": 22.4,
      "x": 60.82,
      "y": 25.73
    },
    {
      "timestamp": 22.6,
      "x": 61.92,
      "y": 25.14
    },
    {
      "timestamp": 22.8,
      "x": 62.16,
      "y": 26.43
    },
    {
      "timestamp": 23.0,
      "x": 63.25,
      "y": 27.1
    },
    {
      "timestamp": 23.2,
      "x": 62.61,
      "y": 27.32
    },
    {
      "timestamp": 23.4,
      "x": 62.7,
      "y": 26.65
    },
    {
      "timestamp": 23.6,
      "x": 62.66,
      "y": 27.92
    },
    {
      "timestamp": 23.8,
      "x": 61.82,
      "y": 26.67
    },
    {
      "timestamp": 24.0,
      "x": 60.42,
      "y": 26.75
    },
    {
      "timestamp": 24.2,
      "x": 61.76,
      "y": 26.08
    },
    {
      "timestamp": 24.4,
      "x": 60.41,
      "y": 26.89
    },
    {
      "timestamp": 24.6,
      "x": 61.4,
      "y": 27.05
    },
    {
      "timestamp": 24.8,
      "x": 61.84,
      "y": 26.33
    },
    {
      "timestamp": 25.0,
      "x": 63.25,
      "y": 25.48
    },
    {
      "timestamp": 25.2,
      "x": 62.54,
      "y": 25.66
    },
    {
      "timestamp": 25.4,
      "x": 62.01,
      "y": 25.42
    },
    {
      "timestamp": 25.6,
      "x": 63.12,
      "y": 24.13
    },
    {
      "timestamp": 25.8,
      "x": 63.88,
      "y": 22.67
    },
    {
      "timestamp": 26.0,
      "x": 63.11,
      "y": 22.62
    },
    {
      "timestamp": 26.2,
      "x": 62.79,
      "y": 23.33
    },
    {
      "timestamp": 26.4,
      "x": 61.73,
      "y": 22.23
    },
    {
      "timestamp": 26.6,
      "x": 60.42,
      "y": 23.54
    },
    {
      "timestamp": 26.8,
      "x": 60.5,
      "y": 22.62
    },
    {
      "timestamp": 27.0,
      "x": 61.85,
      "y": 23.94
    },
    {
      "timestamp": 27.2,
      "x": 61.41,
      "y": 23.09
    },
    {
      "timestamp": 27.4,
      "x": 61.24,
      "y": 24.27
    },
    {
      "timestamp": 27.6,
      "x": 61.68,
      "y": 23.05
    },
    {
      "timestamp": 27.8,
      "x": 61.55,
      "y": 22.68
    },
    {
      "timestamp": 28.0,
      "x": 60.79,
      "y": 22.16
    },
    {
      "timestamp": 28.2,
      "x": 61.97,
      "y": 21.83
    },
    {
      "timestamp": 28.4,
      "x": 60.56,
      "y": 20.45
    },
    {
      "timestamp": 28.6,
      "x": 60.28,
      "y": 19.89
    },
    {
      "timestamp": 28.8,
      "x": 59.2,
      "y": 18.65
    },
    {
      "timestamp": 29.0,
      "x": 58.37,
      "y": 19.3
    },
    {
      "timestamp": 29.2,
      "x": 57.04,
      "y": 20.18
    },
    {
      "timestamp": 29.4,
      "x": 58.34,
      "y": 18.76
    },
    {
      "timestamp": 29.6,
      "x": 58.2,
      "y": 19.74
    },
    {
      "timestamp": 29.8,
      "x": 58.95,
      "y": 18.71
    },
    {
      "timestamp": 30.0,
      "x": 60.44,
      "y": 18.79
    },
    {
      "timestamp": 30.2,
      "x": 61.22,
      "y": 19.28
    },
    {
      "timestamp": 30.4,
      "x": 60.62,
      "y": 18.73
    },
    {
      "timestamp": 30.6,
      "x": 59.9,
      "y": 17.65
    },
    {
      "timestamp": 30.8,
      "x": 59.95,
      "y": 18.0
    },
    {
      "timestamp": 31.0,
      "x": 60.54,
      "y": 18.13
    },
    {
      "timestamp": 31.2,
      "x": 61.45,
      "y": 17.8
    },
    {
      "timestamp": 31.4,
      "x": 61.33,
      "y": 19.06
    },
    {
      "timestamp": 31.6,
      "x": 62.02,
      "y": 18.9
    },
    {
      "timestamp": 31.8,
      "x": 62.47,
      "y": 20.19
    },
    {
      "timestamp": 32.0,
      "x": 62.06,
      "y": 19.2
    },
    {
      "timestamp": 32.2,
      "x": 63.22,
      "y": 20.17
    },
    {
      "timestamp": 32.4,
      "x": 64.71,
      "y": 21.07
    },
    {
      "timestamp": 32.6,
      "x": 64.48,
      "y": 21.87
    },
    {
      "timestamp": 32.8,
      "x": 64.91,
      "y": 20.62
    },
    {
      "timestamp": 33.0,
      "x": 64.5,
      "y": 20.67
    },
    {
      "timestamp": 33.2,
      "x": 64.28,
      "y": 19.94
    },
    {
      "timestamp": 33.4,
      "x": 63.91,
      "y": 20.66
    },
    {
      "timestamp": 33.6,
      "x": 64.37,
      "y": 19.81
    },
    {
      "timestamp": 33.8,
      "x": 63.04,
      "y": 20.13
    },
    {
      "timestamp": 34.0,
      "x": 61.9,
      "y": 21.1
    },
    {
      "timestamp": 34.2,
      "x": 62.25,
      "y": 22.18
    },
    {
      "timestamp": 34.4,
      "x": 61.94,
      "y": 22.93
    },
    {
      "timestamp": 34.6,
      "x": 61.86,
      "y": 22.83
    },
    {
      "timestamp": 34.8,
      "x": 61.6,
      "y": 23.36
    },
    {
      "timestamp": 35.0,
      "x": 60.86,
      "y": 22.63
    },
    {
      "timestamp": 35.2,
      "x": 60.2,
      "y": 21.95
    },
    {
      "timestamp": 35.4,
      "x": 59.51,
      "y": 21.31
    },
    {
      "timestamp": 35.6,
      "x": 60.84,
      "y": 19.98
    },
    {
      "timestamp": 35.8,
      "x": 60.02,
      "y": 20.43
    },
    {
      "timestamp": 36.0,
      "x": 61.42,
      "y": 20.34
    },
    {
      "timestamp": 36.2,
      "x": 61.64,
      "y": 20.29
    },
    {
      "timestamp": 36.4,
      "x": 61.4,
      "y": 21.76
    },
    {
      "timestamp": 36.6,
      "x": 62.71,
      "y": 22.53
    },
    {
      "timestamp": 36.8,
      "x": 63.58,
      "y": 22.71
    },
    {
      "timestamp": 37.0,
      "x": 63.51,
      "y": 22.27
    },
    {
      "timestamp": 37.2,
      "x": 62.59,
      "y": 21.52
    },
    {
      "timestamp": 37.4,
      "x": 63.88,
      "y": 21.91
    },
    {
      "timestamp": 37.6,
      "x": 64.9,
      "y": 20.75
    },
    {
      "timestamp": 37.8,
      "x": 64.93,
      "y": 21.14
    },
    {
      "timestamp": 38.0,
      "x": 63.99,
      "y": 20.37
    },
    {
      "timestamp": 38.2,
      "x": 65.1,
      "y": 21.36
    },
    {
      "timestamp": 38.4,
      "x": 63.81,
      "y": 22.5
    },
    {
      "timestamp": 38.6,
      "x": 63.93,
      "y": 21.57
    },
    {
      "timestamp": 38.8,
      "x": 63.91,
      "y": 23.04
    },
    {
      "timestamp": 39.0,
      "x": 65.3,
      "y": 22.41
    },
    {
      "timestamp": 39.2,
      "x": 64.75,
      "y": 22.94
    },
    {
      "timestamp": 39.4,
      "x": 63.59,
      "y": 22.81
    },
    {
      "timestamp": 39.6,
      "x": 64.99,
      "y": 22.06
    },
    {
      "timestamp": 39.8,
      "x": 65.31,
      "y": 22.8
    },
    {
      "timestamp": 40.0,
      "x": 66.36,
      "y": 23.11
    },
    {
      "timestamp": 40.2,
      "x": 65.04,
      "y": 22.45
    },
    {
      "timestamp": 40.4,
      "x": 64.65,
      "y": 23.23
    },
    {
      "timestamp": 40.6,
      "x": 63.27,
      "y": 23.08
    },
    {
      "timestamp": 40.8,
      "x": 62.73,
      "y": 22.6
    },
    {
      "timestamp": 41.0,
      "x": 62.47,
      "y": 23.0
    },
    {
      "timestamp": 41.2,
      "x": 61.14,
      "y": 22.11
    },
    {
      "timestamp": 41.4,
      "x": 62.06,
      "y": 21.52
    },
    {
      "timestamp": 41.6,
      "x": 62.52,
      "y": 22.31
    },
    {
      "timestamp": 41.8,
      "x": 62.55,
      "y": 23.14
    },
    {
      "timestamp": 42.0,
      "x": 62.07,
      "y": 22.48
    },
    {
      "timestamp": 42.2,
      "x": 62.0,
      "y": 22.06
    },
    {
      "timestamp": 42.4,
      "x": 62.32,
      "y": 23.52
    },
    {
      "timestamp": 42.6,
      "x": 63.81,
      "y": 24.66
    },
    {
      "timestamp": 42.8,
      "x": 64.31,
      "y": 23.69
    },
    {
      "timestamp": 43.0,
      "x": 64.94,
      "y": 23.61
    },
    {
      "timestamp": 43.2,
      "x": 64.24,
      "y": 24.59
    },
    {
      "timestamp": 43.4,
      "x": 65.04,
      "y": 25.35
    },
    {
      "timestamp": 43.6,
      "x": 64.16,
      "y": 24.16
    },
    {
      "timestamp": 43.8,
      "x": 64.02,
      "y": 25.5
    },
    {
      "timestamp": 44.0,
      "x": 65.14,
      "y": 25.87
    },
    {
      "timestamp": 44.2,
      "x": 66.2,
      "y": 27.15
    },
    {
      "timestamp": 44.4,
      "x": 67.47,
      "y": 26.48
    },
    {
      "timestamp": 44.6,
      "x": 67.79,
      "y": 27.2
    },
    {
      "timestamp": 44.8,
      "x": 67.73,
      "y": 27.15
    },
    {
      "timestamp": 45.0,
      "x": 68.31,
      "y": 27.97
    },
    {
      "timestamp": 45.2,
      "x": 69.75,
      "y": 27.32
    },
    {
      "timestamp": 45.4,
      "x": 70.18,
      "y": 26.84
    },
    {
      "timestamp": 45.6,
      "x": 69.47,
      "y": 26.86
    },
    {
      "timestamp": 45.8,
      "x": 69.99,
      "y": 28.24
    },
    {
      "timestamp": 46.0,
      "x": 68.72,
      "y": 28.9
    },
    {
      "timestamp": 46.2,
      "x": 67.84,
      "y": 30.2
    },
    {
      "timestamp": 46.4,
      "x": 68.97,
      "y": 29.76
    },
    {
      "timestamp": 46.6,
      "x": 68.79,
      "y": 28.73
    },
    {
      "timestamp": 46.8,
      "x": 69.4,
      "y": 28.57
    },
    {
      "timestamp": 47.0,
      "x": 70.44,
      "y": 29.57
    },
    {
      "timestamp": 47.2,
      "x": 71.54,
      "y": 29.29
    },
    {
      "timestamp": 47.4,
      "x": 71.93,
      "y": 28.68
    },
    {
      "timestamp": 47.6,
      "x": 72.82,
      "y": 30.08
    },
    {
      "timestamp": 47.8,
      "x": 72.1,
      "y": 31.17
    },
    {
      "timestamp": 48.0,
      "x": 72.75,
      "y": 30.95
    },
    {
      "timestamp": 48.2,
      "x": 72.0,
      "y": 30.32
    },
    {
      "timestamp": 48.4,
      "x": 73.46,
      "y": 31.24
    },
    {
      "timestamp": 48.6,
      "x": 74.53,
      "y": 29.79
    },
    {
      "timestamp": 48.8,
      "x": 75.69,
      "y": 30.08
    },
    {
      "timestamp": 49.0,
      "x": 76.59,
      "y": 29.07
    },
    {
      "timestamp": 49.2,
      "x": 76.48,
      "y": 28.32
    },
    {
      "timestamp": 49.4,
      "x": 75.35,
      "y": 29.02
    },
    {
      "timestamp": 49.6,
      "x": 74.41,
      "y": 28.61
    },
    {
      "timestamp": 49.8,
      "x": 74.68,
      "y": 29.69
    },
    {
      "timestamp": 50.0,
      "x": 74.27,
      "y": 30.8
    },
    {
      "timestamp": 50.2,
      "x": 74.02,
      "y": 30.83
    },
    {
      "timestamp": 50.4,
      "x": 74.94,
      "y": 30.43
    },
    {
      "timestamp": 50.6,
      "x": 74.21,
      "y": 29.96
    },
    {
      "timestamp": 50.8,
      "x": 75.25,
      "y": 31.38
    },
    {
      "timestamp": 51.0,
      "x": 75.22,
      "y": 30.07
    },
    {
      "timestamp": 51.2,
      "x": 75.11,
      "y": 30.09
    },
    {
      "timestamp": 51.4,
      "x": 73.95,
      "y": 29.1
    },
    {
      "timestamp": 51.6,
      "x": 74.31,
      "y": 29.04
    },
    {
      "timestamp": 51.8,
      "x": 73.13,
      "y": 29.48
    },
    {
      "timestamp": 52.0,
      "x": 73.88,
      "y": 30.11
    },
    {
      "timestamp": 52.2,
      "x": 74.71,
      "y": 28.94
    },
    {
      "timestamp": 52.4,
      "x": 73.42,
      "y": 27.5
    },
    {
      "timestamp": 52.6,
      "x": 72.35,
      "y": 26.56
    },
    {
      "timestamp": 52.8,
      "x": 73.73,
      "y": 26.98
    },
    {
      "timestamp": 53.0,
      "x": 73.82,
      "y": 28.22
    },
    {
      "timestamp": 53.2,
      "x": 74.06,
      "y": 27.65
    },
    {
      "timestamp": 53.4,
      "x": 73.94,
      "y": 26.89
    },
    {
      "timestamp": 53.6,
      "x": 74.31,
      "y": 27.38
    },
    {
      "timestamp": 53.8,
      "x": 73.04,
      "y": 28.13
    },
    {
      "timestamp": 54.0,
      "x": 72.1,
      "y": 28.94
    },
    {
      "timestamp": 54.2,
      "x": 71.35,
      "y": 30.38
    },
    {
      "timestamp": 54.4,
      "x": 72.18,
      "y": 29.24
    },
    {
      "timestamp": 54.6,
      "x": 73.22,
      "y": 28.6
    },
    {
      "timestamp": 54.8,
      "x": 73.39,
      "y": 27.52
    },
    {
      "timestamp": 55.0,
      "x": 72.45,
      "y": 28.36
    },
    {
      "timestamp": 55.2,
      "x": 71.57,
      "y": 29.77
    },
    {
      "timestamp": 55.4,
      "x": 71.06,
      "y": 28.49
    },
    {
      "timestamp": 55.6,
      "x": 70.76,
      "y": 28.44
    },
    {
      "timestamp": 55.8,
      "x": 69.64,
      "y": 28.29
    },
    {
      "timestamp": 56.0,
      "x": 68.95,
      "y": 28.69
    },
    {
      "timestamp": 56.2,
      "x": 67.66,
      "y": 27.5
    },
    {
      "timestamp": 56.4,
      "x": 69.1,
      "y": 28.86
    },
    {
      "timestamp": 56.6,
      "x": 68.26,
      "y": 27.4
    },
    {
      "timestamp": 56.8,
      "x": 68.59,
      "y": 26.81
    },
    {
      "timestamp": 57.0,
      "x": 69.18,
      "y": 27.35
    },
    {
      "timestamp": 57.2,
      "x": 69.62,
      "y": 27.11
    },
    {
      "timestamp": 57.4,
      "x": 70.01,
      "y": 27.16
    },
    {
      "timestamp": 57.6,
      "x": 70.32,
      "y": 27.07
    },
    {
      "timestamp": 57.8,
      "x": 70.65,
      "y": 27.27
    },
    {
      "timestamp": 58.0,
      "x": 71.43,
      "y": 26.67
    },
    {
      "timestamp": 58.2,
      "x": 71.34,
      "y": 27.22
    },
    {
      "timestamp": 58.4,
      "x": 69.87,
      "y": 27.39
    },
    {
      "timestamp": 58.6,
      "x": 69.0,
      "y": 27.91
    },
    {
      "timestamp": 58.8,
      "x": 69.48,
      "y": 27.65
    },
    {
      "timestamp": 59.0,
      "x": 69.19,
      "y": 26.49
    },
    {
      "timestamp": 59.2,
      "x": 68.32,
      "y": 27.61
    },
    {
      "timestamp": 59.4,
      "x": 68.36,
      "y": 27.6
    },
    {
      "timestamp": 59.6,
      "x": 69.64,
      "y": 27.52
    },
    {
      "timestamp": 59.8,
      "x": 69.7,
      "y": 27.71
    },
    {
      "timestamp": 60.0,
      "x": 70.46,
      "y": 26.33
    },
    {
      "timestamp": 60.2,
      "x": 69.48,
      "y": 25.2
    },
    {
      "timestamp": 60.4,
      "x": 68.95,
      "y": 23.71
    },
    {
      "timestamp": 60.6,
      "x": 68.39,
      "y": 22.42
    },
    {
      "timestamp": 60.8,
      "x": 69.5,
      "y": 21.47
    },
    {
      "timestamp": 61.0,
      "x": 69.27,
      "y": 21.35
    },
    {
      "timestamp": 61.2,
      "x": 70.48,
      "y": 21.7
    },
    {
      "timestamp": 61.4,
      "x": 69.56,
      "y": 22.02
    },
    {
      "timestamp": 61.6,
      "x": 70.7,
      "y": 20.79
    },
    {
      "timestamp": 61.8,
      "x": 72.04,
      "y": 19.58
    },
    {
      "timestamp": 62.0,
      "x": 71.56,
      "y": 19.0
    },
    {
      "timestamp": 62.2,
      "x": 72.2,
      "y": 18.79
    },
    {
      "timestamp": 62.4,
      "x": 70.86,
      "y": 19.5
    },
    {
      "timestamp": 62.6,
      "x": 69.46,
      "y": 19.58
    },
    {
      "timestamp": 62.8,
      "x": 69.17,
      "y": 19.45
    },
    {
      "timestamp": 63.0,
      "x": 68.85,
      "y": 20.84
    },
    {
      "timestamp": 63.2,
      "x": 67.76,
      "y": 20.91
    },
    {
      "timestamp": 63.4,
      "x": 67.22,
      "y": 22.27
    },
    {
      "timestamp": 63.6,
      "x": 66.66,
      "y": 20.83
    },
    {
      "timestamp": 63.8,
      "x": 67.26,
      "y": 19.94
    },
    {
      "timestamp": 64.0,
      "x": 67.47,
      "y": 20.13
    },
    {
      "timestamp": 64.2,
      "x": 66.48,
      "y": 19.57
    },
    {
      "timestamp": 64.4,
      "x": 65.29,
      "y": 19.37
    },
    {
      "timestamp": 64.6,
      "x": 65.22,
      "y": 18.57
    },
    {
      "timestamp": 64.8,
      "x": 66.17,
      "y": 18.14
    },
    {
      "timestamp": 65.0,
      "x": 64.77,
      "y": 18.82
    },
    {
      "timestamp": 65.2,
      "x": 65.8,
      "y": 20.17
    },
    {
      "timestamp": 65.4,
      "x": 67.08,
      "y": 19.94
    },
    {
      "timestamp": 65.6,
      "x": 66.07,
      "y": 21.02
    },
    {
      "timestamp": 65.8,
      "x": 66.35,
      "y": 21.72
    },
    {
      "timestamp": 66.0,
      "x": 65.16,
      "y": 21.18
    },
    {
      "timestamp": 66.2,
      "x": 66.16,
      "y": 20.19
    },
    {
      "timestamp": 66.4,
      "x": 67.37,
      "y": 18.82
    },
    {
      "timestamp": 66.6,
      "x": 68.85,
      "y": 18.72
    },
    {
      "timestamp": 66.8,
      "x": 67.87,
      "y": 17.41
    },
    {
      "timestamp": 67.0,
      "x": 66.91,
      "y": 18.6
    },
    {
      "timestamp": 67.2,
      "x": 66.81,
      "y": 19.76
    },
    {
      "timestamp": 67.4,
      "x": 66.29,
      "y": 21.12
    },
    {
      "timestamp": 67.6,
      "x": 66.69,
      "y": 20.25
    },
    {
      "timestamp": 67.8,
      "x": 65.94,
      "y": 18.96
    },
    {
      "timestamp": 68.0,
      "x": 64.62,
      "y": 19.96
    },
    {
      "timestamp": 68.2,
      "x": 65.64,
      "y": 18.65
    },
    {
      "timestamp": 68.4,
      "x": 66.4,
      "y": 20.12
    },
    {
      "timestamp": 68.6,
      "x": 66.15,
      "y": 19.49
    },
    {
      "timestamp": 68.8,
      "x": 65.58,
      "y": 19.21
    },
    {
      "timestamp": 69.0,
      "x": 66.57,
      "y": 18.62
    },
    {
      "timestamp": 69.2,
      "x": 66.75,
      "y": 17.61
    },
    {
      "timestamp": 69.4,
      "x": 65.26,
      "y": 16.25
    },
    {
      "timestamp": 69.6,
      "x": 66.4,
      "y": 15.54
    },
    {
      "timestamp": 69.8,
      "x": 65.39,
      "y": 16.04
    },
    {
      "timestamp": 70.0,
      "x": 65.88,
      "y": 15.11
    },
    {
      "timestamp": 70.2,
      "x": 65.7,
      "y": 15.16
    },
    {
      "timestamp": 70.4,
      "x": 66.26,
      "y": 13.98
    },
    {
      "timestamp": 70.6,
      "x": 67.15,
      "y": 13.95
    },
    {
      "timestamp": 70.8,
      "x": 66.1,
      "y": 14.89
    },
    {
      "timestamp": 71.0,
      "x": 64.84,
      "y": 15.46
    },
    {
      "timestamp": 71.2,
      "x": 65.67,
      "y": 16.37
    },
    {
      "timestamp": 71.4,
      "x": 66.67,
      "y": 16.77
    },
    {
      "timestamp": 71.6,
      "x": 67.99,
      "y": 15.83
    },
    {
      "timestamp": 71.8,
      "x": 67.86,
      "y": 15.71
    },
    {
      "timestamp": 72.0,
      "x": 69.26,
      "y": 15.3
    },
    {
      "timestamp": 72.2,
      "x": 70.21,
      "y": 15.33
    },
    {
      "timestamp": 72.4,
      "x": 71.45,
      "y": 16.62
    },
    {
      "timestamp": 72.6,
      "x": 72.03,
      "y": 16.76
    },
    {
      "timestamp": 72.8,
      "x": 73.08,
      "y": 15.49
    },
    {
      "timestamp": 73.0,
      "x": 71.73,
      "y": 16.79
    },
    {
      "timestamp": 73.2,
      "x": 70.45,
      "y": 16.21
    },
    {
      "timestamp": 73.4,
      "x": 71.19,
      "y": 16.42
    },
    {
      "timestamp": 73.6,
      "x": 72.42,
      "y": 17.14
    },
    {
      "timestamp": 73.8,
      "x": 72.76,
      "y": 17.67
    },
    {
      "timestamp": 74.0,
      "x": 72.62,
      "y": 18.26
    },
    {
      "timestamp": 74.2,
      "x": 73.68,
      "y": 18.08
    },
    {
      "timestamp": 74.4,
      "x": 74.34,
      "y": 18.62
    },
    {
      "timestamp": 74.6,
      "x": 75.08,
      "y": 19.79
    },
    {
      "timestamp": 74.8,
      "x": 73.65,
      "y": 18.5
    },
    {
      "timestamp": 75.0,
      "x": 73.68,
      "y": 19.38
    },
    {
      "timestamp": 75.2,
      "x": 74.16,
      "y": 19.48
    },
    {
      "timestamp": 75.4,
      "x": 74.36,
      "y": 18.19
    },
    {
      "timestamp": 75.6,
      "x": 73.42,
      "y": 17.96
    },
    {
      "timestamp": 75.8,
      "x": 74.05,
      "y": 16.74
    },
    {
      "timestamp": 76.0,
      "x": 74.92,
      "y": 16.96
    },
    {
      "timestamp": 76.2,
      "x": 74.21,
      "y": 16.34
    },
    {
      "timestamp": 76.4,
      "x": 72.84,
      "y": 16.77
    },
    {
      "timestamp": 76.6,
      "x": 71.56,
      "y": 15.34
    },
    {
      "timestamp": 76.8,
      "x": 72.33,
      "y": 16.27
    },
    {
      "timestamp": 77.0,
      "x": 72.42,
      "y": 15.02
    },
    {
      "timestamp": 77.2,
      "x": 71.6,
      "y": 15.38
    },
    {
      "timestamp": 77.4,
      "x": 71.91,
      "y": 14.03
    },
    {
      "timestamp": 77.6,
      "x": 70.51,
      "y": 13.3
    },
    {
      "timestamp": 77.8,
      "x": 70.0,
      "y": 13.14
    },
    {
      "timestamp": 78.0,
      "x": 69.17,
      "y": 13.36
    },
    {
      "timestamp": 78.2,
      "x": 68.37,
      "y": 14.11
    },
    {
      "timestamp": 78.4,
      "x": 68.03,
      "y": 14.28
    },
    {
      "timestamp": 78.6,
      "x": 68.14,
      "y": 15.31
    },
    {
      "timestamp": 78.8,
      "x": 67.25,
      "y": 15.94
    },
    {
      "timestamp": 79.0,
      "x": 67.83,
      "y": 17.11
    },
    {
      "timestamp": 79.2,
      "x": 66.44,
      "y": 17.56
    },
    {
      "timestamp": 79.4,
      "x": 65.15,
      "y": 18.68
    },
    {
      "timestamp": 79.6,
      "x": 66.22,
      "y": 19.04
    },
    {
      "timestamp": 79.8,
      "x": 67.4,
      "y": 17.98
    },
    {
      "timestamp": 80.0,
      "x": 68.36,
      "y": 18.94
    },
    {
      "timestamp": 80.2,
      "x": 68.88,
      "y": 17.93
    },
    {
      "timestamp": 80.4,
      "x": 67.53,
      "y": 18.29
    },
    {
      "timestamp": 80.6,
      "x": 67.58,
      "y": 19.45
    },
    {
      "timestamp": 80.8,
      "x": 66.3,
      "y": 18.64
    },
    {
      "timestamp": 81.0,
      "x": 66.17,
      "y": 17.73
    },
    {
      "timestamp": 81.2,
      "x": 65.21,
      "y": 19.06
    },
    {
      "timestamp": 81.4,
      "x": 64.4,
      "y": 17.68
    },
    {
      "timestamp": 81.6,
      "x": 64.94,
      "y": 17.94
    },
    {
      "timestamp": 81.8,
      "x": 64.98,
      "y": 18.69
    },
    {
      "timestamp": 82.0,
      "x": 63.78,
      "y": 20.06
    },
    {
      "timestamp": 82.2,
      "x": 63.25,
      "y": 19.7
    },
    {
      "timestamp": 82.4,
      "x": 62.38,
      "y": 20.98
    },
    {
      "timestamp": 82.6,
      "x": 61.33,
      "y": 20.54
    },
    {
      "timestamp": 82.8,
      "x": 62.8,
      "y": 19.39
    },
    {
      "timestamp": 83.0,
      "x": 61.9,
      "y": 20.85
    },
    {
      "timestamp": 83.2,
      "x": 62.6,
      "y": 19.83
    },
    {
      "timestamp": 83.4,
      "x": 63.61,
      "y": 20.58
    },
    {
      "timestamp": 83.6,
      "x": 63.61,
      "y": 21.77
    },
    {
      "timestamp": 83.8,
      "x": 64.02,
      "y": 23.08
    },
    {
      "timestamp": 84.0,
      "x": 64.7,
      "y": 22.57
    },
    {
      "timestamp": 84.2,
      "x": 64.14,
      "y": 23.88
    },
    {
      "timestamp": 84.4,
      "x": 62.78,
      "y": 23.39
    },
    {
      "timestamp": 84.6,
      "x": 61.82,
      "y": 24.51
    },
    {
      "timestamp": 84.8,
      "x": 61.55,
      "y": 23.9
    },
    {
      "timestamp": 85.0,
      "x": 60.14,
      "y": 24.57
    },
    {
      "timestamp": 85.2,
      "x": 58.7,
      "y": 24.48
    },
    {
      "timestamp": 85.4,
      "x": 58.29,
      "y": 24.28
    },
    {
      "timestamp": 85.6,
      "x": 57.6,
      "y": 23.56
    },
    {
      "timestamp": 85.8,
      "x": 58.37,
      "y": 24.28
    },
    {
      "timestamp": 86.0,
      "x": 59.21,
      "y": 23.15
    },
    {
      "timestamp": 86.2,
      "x": 59.91,
      "y": 23.59
    },
    {
      "timestamp": 86.4,
      "x": 59.26,
      "y": 22.28
    },
    {
      "timestamp": 86.6,
      "x": 58.51,
      "y": 22.12
    },
    {
      "timestamp": 86.8,
      "x": 57.25,
      "y": 22.0
    },
    {
      "timestamp": 87.0,
      "x": 58.05,
      "y": 22.57
    },
    {
      "timestamp": 87.2,
      "x": 58.83,
      "y": 23.85
    },
    {
      "timestamp": 87.4,
      "x": 57.68,
      "y": 25.19
    },
    {
      "timestamp": 87.6,
      "x": 58.65,
      "y": 24.55
    },
    {
      "timestamp": 87.8,
      "x": 59.4,
      "y": 25.96
    },
    {
      "timestamp": 88.0,
      "x": 60.43,
      "y": 25.49
    },
    {
      "timestamp": 88.2,
      "x": 60.2,
      "y": 24.32
    },
    {
      "timestamp": 88.4,
      "x": 60.72,
      "y": 23.3
    },
    {
      "timestamp": 88.6,
      "x": 60.88,
      "y": 24.38
    },
    {
      "timestamp": 88.8,
      "x": 60.24,
      "y": 24.76
    },
    {
      "timestamp": 89.0,
      "x": 61.06,
      "y": 26.16
    },
    {
      "timestamp": 89.2,
      "x": 61.32,
      "y": 26.46
    },
    {
      "timestamp": 89.4,
      "x": 62.61,
      "y": 27.29
    },
    {
      "timestamp": 89.6,
      "x": 62.95,
      "y": 26.61
    },
    {
      "timestamp": 89.8,
      "x": 64.28,
      "y": 27.93
    },
    {
      "timestamp": 90.0,
      "x": 63.65,
      "y": 27.71
    },
    {
      "timestamp": 90.2,
      "x": 64.97,
      "y": 28.48
    },
    {
      "timestamp": 90.4,
      "x": 63.63,
      "y": 28.82
    },
    {
      "timestamp": 90.6,
      "x": 63.66,
      "y": 27.33
    },
    {
      "timestamp": 90.8,
      "x": 63.65,
      "y": 26.49
    },
    {
      "timestamp": 91.0,
      "x": 62.27,
      "y": 26.54
    },
    {
      "timestamp": 91.2,
      "x": 62.91,
      "y": 26.8
    },
    {
      "timestamp": 91.4,
      "x": 63.18,
      "y": 25.66
    },
    {
      "timestamp": 91.6,
      "x": 63.46,
      "y": 26.67
    },
    {
      "timestamp": 91.8,
      "x": 64.08,
      "y": 25.72
    },
    {
      "timestamp": 92.0,
      "x": 65.13,
      "y": 26.88
    },
    {
      "timestamp": 92.2,
      "x": 65.38,
      "y": 27.21
    },
    {
      "timestamp": 92.4,
      "x": 64.97,
      "y": 27.43
    },
    {
      "timestamp": 92.6,
      "x": 63.61,
      "y": 28.08
    },
    {
      "timestamp": 92.8,
      "x": 64.23,
      "y": 28.58
    },
    {
      "timestamp": 93.0,
      "x": 63.85,
      "y": 27.2
    },
    {
      "timestamp": 93.2,
      "x": 65.12,
      "y": 28.4
    },
    {
      "timestamp": 93.4,
      "x": 63.95,
      "y": 28.1
    },
    {
      "timestamp": 93.6,
      "x": 63.27,
      "y": 27.96
    },
    {
      "timestamp": 93.8,
      "x": 62.13,
      "y": 28.47
    },
    {
      "timestamp": 94.0,
      "x": 62.85,
      "y": 27.53
    },
    {
      "timestamp": 94.2,
      "x": 63.53,
      "y": 28.11
    },
    {
      "timestamp": 94.4,
      "x": 64.91,
      "y": 29.32
    },
    {
      "timestamp": 94.6,
      "x": 66.33,
      "y": 29.48
    },
    {
      "timestamp": 94.8,
      "x": 66.86,
      "y": 29.7
    },
    {
      "timestamp": 95.0,
      "x": 68.24,
      "y": 29.66
    },
    {
      "timestamp": 95.2,
      "x": 68.83,
      "y": 28.64
    },
    {
      "timestamp": 95.4,
      "x": 68.63,
      "y": 29.88
    },
    {
      "timestamp": 95.6,
      "x": 69.51,
      "y": 30.27
    },
    {
      "timestamp": 95.8,
      "x": 70.51,
      "y": 31.13
    },
    {
      "timestamp": 96.0,
      "x": 70.79,
      "y": 30.34
    },
    {
      "timestamp": 96.2,
      "x": 69.99,
      "y": 29.59
    },
    {
      "timestamp": 96.4,
      "x": 71.25,
      "y": 29.46
    },
    {
      "timestamp": 96.6,
      "x": 71.77,
      "y": 30.24
    },
    {
      "timestamp": 96.8,
      "x": 72.07,
      "y": 30.94
    },
    {
      "timestamp": 97.0,
      "x": 72.44,
      "y": 30.0
    },
    {
      "timestamp": 97.2,
      "x": 72.1,
      "y": 30.14
    },
    {
      "timestamp": 97.4,
      "x": 72.4,
      "y": 29.01
    },
    {
      "timestamp": 97.6,
      "x": 72.59,
      "y": 28.98
    },
    {
      "timestamp": 97.8,
      "x": 71.93,
      "y": 30.05
    },
    {
      "timestamp": 98.0,
      "x": 72.11,
      "y": 29.54
    },
    {
      "timestamp": 98.2,
      "x": 72.4,
      "y": 29.25
    },
    {
      "timestamp": 98.4,
      "x": 70.92,
      "y": 29.11
    },
    {
      "timestamp": 98.6,
      "x": 71.65,
      "y": 28.75
    },
    {
      "timestamp": 98.8,
      "x": 72.25,
      "y": 30.05
    },
    {
      "timestamp": 99.0,
      "x": 71.08,
      "y": 29.93
    },
    {
      "timestamp": 99.2,
      "x": 69.69,
      "y": 29.35
    },
    {
      "timestamp": 99.4,
      "x": 71.17,
      "y": 28.49
    },
    {
      "timestamp": 99.6,
      "x": 71.65,
      "y": 28.47
    },
    {
      "timestamp": 99.8,
      "x": 72.77,
      "y": 29.42
    }
  ]
}